README.md
setup.py
m_logging_dev.egg-info/PKG-INFO
m_logging_dev.egg-info/SOURCES.txt
m_logging_dev.egg-info/dependency_links.txt
m_logging_dev.egg-info/requires.txt
m_logging_dev.egg-info/top_level.txt
mobio/libs/logging/__init__.py
mobio/libs/logging/logging.conf