Metadata-Version: 2.1
Name: m-logging-dev
Version: 1.0.0
Summary: Mobio project SDK
Home-page: UNKNOWN
Author: MOBIO
Author-email: contact@mobio.io
License: UNKNOWN
Platform: UNKNOWN
Requires-Python: >=3.8
